[
  {
    "name": "Strength",
    "description": "Physical power and might.",
    "image": "https://characternexus.blob.core.windows.net/resources/EverydayHeroes/Attr_Strength.jpg",
    "value": 8
  },
  {
    "name": "Dexterity",
    "description": "Ability to move gracefully.",
    "image": "https://characternexus.blob.core.windows.net/resources/EverydayHeroes/Attr_Dexterity.jpg",
    "value": 8
  },
  {
    "name": "Constitution",
    "description": "Physical health and endurance.",
    "image": "https://characternexus.blob.core.windows.net/resources/EverydayHeroes/Attr_Constitution.jpg",
    "value": 8
  },
  {
    "name": "Intelligence",
    "description": "Reasoning ability and wits.",
    "image": "https://characternexus.blob.core.windows.net/resources/EverydayHeroes/Attr_Intelligence.jpg",
    "value": 8
  },
  {
    "name": "Wisdom",
    "description": "Intuitive understanding and spiritualism.",
    "image": "https://characternexus.blob.core.windows.net/resources/EverydayHeroes/Attr_Wisdom.jpg",
    "value": 8
  },
  {
    "name": "Charisma",
    "description": "Personal magnetism and ego.",
    "image": "https://characternexus.blob.core.windows.net/resources/EverydayHeroes/Attr_Charisma.jpg",
    "value": 8
  }
]